LICENSE
MANIFEST.in
README.md
setup.py
python_jmeter/__init__.py
python_jmeter/builder.py
python_jmeter/parser.py
python_jmeter/runner.py
python_jmeter.egg-info/PKG-INFO
python_jmeter.egg-info/SOURCES.txt
python_jmeter.egg-info/dependency_links.txt
python_jmeter.egg-info/top_level.txt
python_jmeter.egg-info/zip-safe