Metadata-Version: 2.1
Name: python-jmeter
Version: 0.1
Summary: build jmx and run jmeter by python
Home-page: https://github.com/hanzhichao/python_jmeter
Author: Han Zhichao
Author-email: superhin@126.com
License: MIT license
Keywords: python-jmeter,jmeter,jmx
Platform: UNKNOWN
Classifier: Programming Language :: Python
Classifier: Programming Language :: Python :: 2.7
Classifier: Programming Language :: Python :: 3.7
License-File: LICENSE
